setup.py
PTEA/__init__.py
PTEA/network.py
PTEA.egg-info/PKG-INFO
PTEA.egg-info/SOURCES.txt
PTEA.egg-info/dependency_links.txt
PTEA.egg-info/top_level.txt