Metadata-Version: 2.1
Name: PTEA
Version: 0.0.1
Summary: 原始模型
Home-page: https://github.com/
Author: Fanstandy
Author-email: 2806481560@qq.com
License: UNKNOWN
Platform: UNKNOWN
Classifier: Programming Language :: Python :: 3
Classifier: License :: OSI Approved :: MIT License
Classifier: Operating System :: OS Independent
